sdf/__init__.py
sdf/__main__.py
sdf/_version.py
sdf/aws_sdf.py
sdf/azure_sdf.py
sdf/gcp_sdf.py
sdf/utils.py
sankir_sdf-0.0.11.dist-info/METADATA
sankir_sdf-0.0.11.dist-info/WHEEL
sankir_sdf-0.0.11.dist-info/entry_points.txt
sankir_sdf-0.0.11.dist-info/top_level.txt
sankir_sdf-0.0.11.dist-info/RECORD
