Metadata-Version: 2.1
Name: sankir-sdf
Version: 0.0.11
Summary: SDF Converter
Home-page: https://github.com/SanKirTech/sdf-converter
Author: SanKir Technologies Pvt Ltd
Author-email: sanjay@sankir.com
License: UNKNOWN
Platform: UNKNOWN
Classifier: Programming Language :: Python :: 3
Classifier: License :: OSI Approved :: MIT License
Classifier: Operating System :: OS Independent
Requires-Python: >=3.6
Requires-Dist: google-cloud-storage
Requires-Dist: google-cloud-bigquery
Requires-Dist: boto3
Requires-Dist: pandas
Requires-Dist: azure-storage-blob (==12.9.0)
